odoo/addons/hr_maintenance_workspace/README.rst
odoo/addons/hr_maintenance_workspace/__init__.py
odoo/addons/hr_maintenance_workspace/__manifest__.py
odoo/addons/hr_maintenance_workspace/i18n/hr_maintenance_workspace.pot
odoo/addons/hr_maintenance_workspace/i18n/it.po
odoo/addons/hr_maintenance_workspace/models/__init__.py
odoo/addons/hr_maintenance_workspace/models/equipment.py
odoo/addons/hr_maintenance_workspace/models/hr_employee.py
odoo/addons/hr_maintenance_workspace/models/workspace.py
odoo/addons/hr_maintenance_workspace/readme/CONTRIBUTORS.rst
odoo/addons/hr_maintenance_workspace/readme/DESCRIPTION.rst
odoo/addons/hr_maintenance_workspace/security/ir.model.access.csv
odoo/addons/hr_maintenance_workspace/static/description/icon.png
odoo/addons/hr_maintenance_workspace/static/description/index.html
odoo/addons/hr_maintenance_workspace/tests/__init__.py
odoo/addons/hr_maintenance_workspace/tests/test_hr_maitenance_workspace.py
odoo/addons/hr_maintenance_workspace/views/hr_employee_views.xml
odoo/addons/hr_maintenance_workspace/views/hr_maintenance_workspace_menu_views.xml
odoo/addons/hr_maintenance_workspace/views/maintenance_views.xml
odoo/addons/hr_maintenance_workspace/views/maintenance_workspace_views.xml
odoo14_addon_hr_maintenance_workspace-14.0.1.0.1.dev4.dist-info/METADATA
odoo14_addon_hr_maintenance_workspace-14.0.1.0.1.dev4.dist-info/WHEEL
odoo14_addon_hr_maintenance_workspace-14.0.1.0.1.dev4.dist-info/top_level.txt
odoo14_addon_hr_maintenance_workspace-14.0.1.0.1.dev4.dist-info/RECORD
